fandango/__init__.py
fandango/_version.py
fandango/api.py
fandango/beartype.py
fandango/cli/__init__.py
fandango/cli/commands.py
fandango/cli/complete.py
fandango/cli/output.py
fandango/cli/parser.py
fandango/cli/progress.py
fandango/cli/shell.py
fandango/cli/utils.py
fandango/constraints/__init__.py
fandango/constraints/base.py
fandango/constraints/comparison.py
fandango/constraints/conjunction.py
fandango/constraints/constraint.py
fandango/constraints/constraint_visitor.py
fandango/constraints/disjunct.py
fandango/constraints/exists.py
fandango/constraints/expression.py
fandango/constraints/failing_tree.py
fandango/constraints/fitness.py
fandango/constraints/forall.py
fandango/constraints/implication.py
fandango/constraints/predicates.py
fandango/constraints/repetition_bounds.py
fandango/constraints/soft.py
fandango/converters/antlr/ANTLRFandangoConverter.py
fandango/converters/antlr/ANTLRv4Lexer.g4
fandango/converters/antlr/ANTLRv4Lexer.interp
fandango/converters/antlr/ANTLRv4Lexer.py
fandango/converters/antlr/ANTLRv4Lexer.tokens
fandango/converters/antlr/ANTLRv4LexerOrig.g4
fandango/converters/antlr/ANTLRv4Parser.g4
fandango/converters/antlr/ANTLRv4Parser.interp
fandango/converters/antlr/ANTLRv4Parser.py
fandango/converters/antlr/ANTLRv4Parser.tokens
fandango/converters/antlr/ANTLRv4ParserVisitor.py
fandango/converters/antlr/Calculator.g4
fandango/converters/antlr/LexerAdaptor.py
fandango/converters/antlr/Makefile
fandango/converters/antlr/mypy.ini
fandango/converters/antlr/predefined.tokens
fandango/converters/bt/BTFandangoConverter.py
fandango/converters/bt/gif.bt
fandango/converters/dtd/DTDFandangoConverter.py
fandango/converters/dtd/Smiley.svg
fandango/converters/dtd/Smiley.svg.txt
fandango/converters/dtd/svg.fan
fandango/converters/dtd/svg11-flat-20110816.dtd
fandango/converters/dtd/svg11.fan
fandango/converters/dtd/svgextreme.fan
fandango/converters/fan/FandangoFandangoConverter.py
fandango/converters/FandangoConverter.py
fandango/errors.py
fandango_fuzzer-1.0.6.dist-info/METADATA
fandango_fuzzer-1.0.6.dist-info/WHEEL
fandango_fuzzer-1.0.6.dist-info/entry_points.txt
fandango_fuzzer-1.0.6.dist-info/licenses/LICENSE.md
fandango_fuzzer-1.0.6.dist-info/RECORD
