Metadata-Version: 2.2
Name: fandango-fuzzer
Version: 1.0.6
Summary: Fandango produces myriads of high-quality random inputs to test programs, giving users unprecedented control over format and shape of the inputs.
Author-Email: =?utf-8?q?Jos=C3=A9_Antonio_Zamudio_Amaya?= <jose.zamudio@cispa.de>, Marius Smytzek <marius.smytzek@cispa.de>, Andreas Zeller <andreas.zeller@cispa.de>
License: European Union Public Licence
Classifier: Intended Audience :: Science/Research
Classifier: Programming Language :: Python :: 3.10
Classifier: Programming Language :: Python :: 3.11
Classifier: Programming Language :: Python :: 3.12
Classifier: Programming Language :: Python :: 3.13
Classifier: Operating System :: OS Independent
Classifier: Topic :: Scientific/Engineering
Classifier: Topic :: Software Development :: Testing
Project-URL: homepage, https://fandango-fuzzer.github.io/
Project-URL: repository, https://github.com/fandango-fuzzer/fandango/
Project-URL: Bug Tracker, https://github.com/fandango-fuzzer/fandango/issues
Requires-Python: <4.0,>=3.10
Requires-Dist: ansi_styles>=0.2.2
Requires-Dist: antlr4-python3-runtime>=4.13
Requires-Dist: cachedir_tag>=0.0.3
Requires-Dist: dill>=0.3.7
Requires-Dist: exrex>=0.12.0
Requires-Dist: gnureadline>=8.2.13; platform_system != "Windows" and implementation_name != "pypy"
Requires-Dist: lxml>=5.3.2
Requires-Dist: py010parser>=0.1.18
Requires-Dist: pyreadline3>=3.5.4; platform_system == "Windows"
Requires-Dist: regex>=2024.11.6
Requires-Dist: tdigest>=0.5.2.2
Requires-Dist: thefuzz>=0.22
Requires-Dist: xdg-base-dirs>=6.0.2
Requires-Dist: beartype>=0.21.0
Provides-Extra: test
Requires-Dist: Faker>=30.4.0; extra == "test"
Requires-Dist: pytest>=8.3.5; extra == "test"
Requires-Dist: pytest-cov>=4.1.0; extra == "test"
Requires-Dist: pytest-html>=3.2.0; extra == "test"
Requires-Dist: pytest-rerunfailures>=11.1.2; extra == "test"
Requires-Dist: pytest-timeout>=2.4.0; extra == "test"
Requires-Dist: pytest-xdist>=3.7.0; extra == "test"
Requires-Dist: python-dateutil>=2.9.0.post0; extra == "test"
Requires-Dist: docutils==0.21.2; extra == "test"
Requires-Dist: tccbox>=2025.6.6; extra == "test"
Provides-Extra: development
Requires-Dist: fandango-fuzzer[test]; extra == "development"
Requires-Dist: black>=25.1.0; extra == "development"
Requires-Dist: mypy>=1.16.0; extra == "development"
Requires-Dist: pre-commit>=4.2.0; extra == "development"
Requires-Dist: pygls>=2.0.0a4; extra == "development"
Requires-Dist: speedy-antlr-tool>=1.4.3; extra == "development"
Requires-Dist: scikit-build>=0.17.0; extra == "development"
Requires-Dist: cmake>=3.18; extra == "development"
Provides-Extra: book
Requires-Dist: fandango-fuzzer[development]; extra == "book"
Requires-Dist: aiosmtpd>=1.4.6; extra == "book"
Requires-Dist: docutils>=0.20.1; extra == "book"
Requires-Dist: ghp-import>=2.1.0; extra == "book"
Requires-Dist: graphviz>=0.20.3; extra == "book"
Requires-Dist: jupyter-book>=1.0.4; extra == "book"
Requires-Dist: pagelabels>=1.2.1; extra == "book"
Requires-Dist: pyppeteer>=2.0.0; extra == "book"
Requires-Dist: sphinxcontrib-mermaid>=1.0.0; extra == "book"
